AUTHORS
CONTRIBUTING.rst
LICENSE
LICENSE.3RDPARTY
MANIFEST.in
README.rst
SECURITY.md
requirements-testing.txt
requirements.txt
setup.py
demo/README.rst
demo/manage.py
demo/setup.py
demo/demodesk/__init__.py
demo/demodesk/manage.py
demo/demodesk/config/__init__.py
demo/demodesk/config/settings.py
demo/demodesk/config/urls.py
demo/demodesk/config/wsgi.py
demo/demodesk/fixtures/demo.json
demo/demodesk/media/helpdesk/attachments/DH-3/3/someinfo.txt
demo/demodesk/media/helpdesk/attachments/DH-3/4/helpdesk.png
helpdesk/__init__.py
helpdesk/admin.py
helpdesk/apps.py
helpdesk/decorators.py
helpdesk/email.py
helpdesk/exceptions.py
helpdesk/forms.py
helpdesk/lib.py
helpdesk/models.py
helpdesk/query.py
helpdesk/serializers.py
helpdesk/settings.py
helpdesk/tasks.py
helpdesk/templated_email.py
helpdesk/urls.py
helpdesk/user.py
helpdesk/validators.py
helpdesk/fixtures/emailtemplate.json
helpdesk/locale/ar/LC_MESSAGES/django.mo
helpdesk/locale/ar/LC_MESSAGES/django.po
helpdesk/locale/ca/LC_MESSAGES/django.mo
helpdesk/locale/ca/LC_MESSAGES/django.po
helpdesk/locale/cs/LC_MESSAGES/django.mo
helpdesk/locale/cs/LC_MESSAGES/django.po
helpdesk/locale/de/LC_MESSAGES/django.mo
helpdesk/locale/de/LC_MESSAGES/django.po
helpdesk/locale/el/LC_MESSAGES/django.mo
helpdesk/locale/el/LC_MESSAGES/django.po
helpdesk/locale/en/LC_MESSAGES/django.mo
helpdesk/locale/en/LC_MESSAGES/django.po
helpdesk/locale/es/LC_MESSAGES/django.mo
helpdesk/locale/es/LC_MESSAGES/django.po
helpdesk/locale/es_CO/LC_MESSAGES/django.mo
helpdesk/locale/es_CO/LC_MESSAGES/django.po
helpdesk/locale/es_MX/LC_MESSAGES/django.mo
helpdesk/locale/es_MX/LC_MESSAGES/django.po
helpdesk/locale/fa_IR/LC_MESSAGES/django.mo
helpdesk/locale/fa_IR/LC_MESSAGES/django.po
helpdesk/locale/fi/LC_MESSAGES/django.mo
helpdesk/locale/fi/LC_MESSAGES/django.po
helpdesk/locale/fr/LC_MESSAGES/django.mo
helpdesk/locale/fr/LC_MESSAGES/django.po
helpdesk/locale/he_IL/LC_MESSAGES/django.mo
helpdesk/locale/he_IL/LC_MESSAGES/django.po
multitenancy_helpdesk.egg-info/PKG-INFO
multitenancy_helpdesk.egg-info/SOURCES.txt
multitenancy_helpdesk.egg-info/dependency_links.txt
multitenancy_helpdesk.egg-info/not-zip-safe
multitenancy_helpdesk.egg-info/requires.txt
multitenancy_helpdesk.egg-info/top_level.txt