Metadata-Version: 1.2
Name: multitenancy-helpdesk
Version: 0.1.0b5
Summary: A ticket tracker for django-multitenancy helpdesk
Home-page: https://github.com/tekanokhambane/multitenancy-helpdesk
Author: Tekano Khambane
Author-email: tkhambane@gmail.com
Maintainer: Tekano Khambane
Maintainer-email: tkhambane@gmail.com
License: BSD
Keywords: django,helpdesk,multitenancy-helpdesk,tickets,multitenants,incidents,cases,bugs,track,support
Platform: UNKNOWN
Classifier: Development Status :: 4 - Beta
Classifier: Programming Language :: Python
Classifier: Programming Language :: Python :: 3
Classifier: Programming Language :: Python :: 3.8
Classifier: Programming Language :: Python :: 3.9
Classifier: Programming Language :: Python :: 3.10
Classifier: Framework :: Django
Classifier: Framework :: Django :: 3.2
Classifier: Framework :: Django :: 4.0
Classifier: Environment :: Web Environment
Classifier: Operating System :: OS Independent
Classifier: Intended Audience :: Customer Service
Classifier: License :: OSI Approved :: BSD License
Classifier: Topic :: Software Development :: Bug Tracking
Classifier: Topic :: Software Development :: Libraries :: Python Modules
Classifier: Topic :: Office/Business
Classifier: Natural Language :: English
